{
  "metadata": {
    "description": "Zero pose ",
    "user": "k_kravchenko",
    "ctime": "1714978515",
    "version": "1.0.0",
    "references": [],
    "mayaVersion": "2023",
    "mayaSceneFile": "D:/!CW_Rig_n_Anim/!!!!_Rigs/!!!!__BodyTypes/Twister_/mocap/male rigs main.ma"
  }
,
  "objects": {
    "FKIKSpine_M": {
      "attrs": {
        "IKVis": {
          "type": "bool",
          "value": true
        },
        "FKIKBlend": {
          "type": "double",
          "value": 10.0
        },
        "FKVis": {
          "type": "bool",
          "value": true
        }
      }
    },
    "IKSpine1_M": {
      "attrs": {
        "rotateX": {
          "type": "doubleAngle",
          "value": 0.0
        },
        "stiff": {
          "type": "double",
          "value": 0.0
        },
        "FixedOrient": {
          "type": "double",
          "value": 0.0
        },
        "translateZ": {
          "type": "doubleLinear",
          "value": 0.0
        },
        "scaleY": {
          "type": "double",
          "value": 1.0
        },
        "translateX": {
          "type": "doubleLinear",
          "value": 0.0
        },
        "scaleX": {
          "type": "double",
          "value": 1.0
        },
        "translateY": {
          "type": "doubleLinear",
          "value": 0.0
        },
        "rotateZ": {
          "type": "doubleAngle",
          "value": 0.0
        },
        "scaleZ": {
          "type": "double",
          "value": 1.0
        },
        "rotateY": {
          "type": "doubleAngle",
          "value": 0.0
        }
      }
    },
    "FKThumbFinger1_L": {
      "attrs": {
        "rotateX": {
          "type": "doubleAngle",
          "value": 0.0
        },
        "translateZ": {
          "type": "doubleLinear",
          "value": 0.0
        },
        "scaleY": {
          "type": "double",
          "value": 1.0
        },
        "translateX": {
          "type": "doubleLinear",
          "value": 0.0
        },
        "scaleX": {
          "type": "double",
          "value": 1.0
        },
        "translateY": {
          "type": "doubleLinear",
          "value": 0.0
        },
        "rotateZ": {
          "type": "doubleAngle",
          "value": 0.0
        },
        "scaleZ": {
          "type": "double",
          "value": 1.0
        },
        "rotateY": {
          "type": "doubleAngle",
          "value": 0.0
        }
      }
    },
    "FKIKLeg_R": {
      "attrs": {
        "IKVis": {
          "type": "bool",
          "value": true
        },
        "FKIKBlend": {
          "type": "double",
          "value": 10.0
        },
        "FKVis": {
          "type": "bool",
          "value": true
        }
      }
    },
    "FKIndexFinger3_L": {
      "attrs": {
        "rotateX": {
          "type": "doubleAngle",
          "value": 0.0
        },
        "translateZ": {
          "type": "doubleLinear",
          "value": 0.0
        },
        "scaleY": {
          "type": "double",
          "value": 1.0
        },
        "translateX": {
          "type": "doubleLinear",
          "value": 0.0
        },
        "scaleX": {
          "type": "double",
          "value": 1.0
        },
        "translateY": {
          "type": "doubleLinear",
          "value": 0.0
        },
        "rotateZ": {
          "type": "doubleAngle",
          "value": 0.0
        },
        "scaleZ": {
          "type": "double",
          "value": 1.0
        },
        "rotateY": {
          "type": "doubleAngle",
          "value": 0.0
        }
      }
    },
    "AimEye_M": {
      "attrs": {
        "visibility": {
          "type": "bool",
          "value": true
        },
        "translateZ": {
          "type": "doubleLinear",
          "value": 0.0
        },
        "scaleY": {
          "type": "double",
          "value": 1.0
        },
        "translateX": {
          "type": "doubleLinear",
          "value": 0.0
        },
        "scaleX": {
          "type": "double",
          "value": 1.0
        },
        "translateY": {
          "type": "doubleLinear",
          "value": 0.0
        },
        "rotateZ": {
          "type": "doubleAngle",
          "value": 0.0
        },
        "follow": {
          "type": "double",
          "value": 10.0
        },
        "scaleZ": {
          "type": "double",
          "value": 1.0
        },
        "rotateY": {
          "type": "doubleAngle",
          "value": 0.0
        },
        "rotateX": {
          "type": "doubleAngle",
          "value": 0.0
        }
      }
    },
    "PoleArm_R": {
      "attrs": {
        "translateZ": {
          "type": "doubleLinear",
          "value": 0.0
        },
        "translateX": {
          "type": "doubleLinear",
          "value": 0.0
        },
        "lock": {
          "type": "double",
          "value": 0.0
        },
        "translateY": {
          "type": "doubleLinear",
          "value": 0.0
        },
        "follow": {
          "type": "double",
          "value": 0.0
        }
      }
    },
    "FKThumbFinger2_R": {
      "attrs": {
        "rotateX": {
          "type": "doubleAngle",
          "value": 0.0
        },
        "translateZ": {
          "type": "doubleLinear",
          "value": 0.0
        },
        "scaleY": {
          "type": "double",
          "value": 1.0
        },
        "translateX": {
          "type": "doubleLinear",
          "value": 0.0
        },
        "scaleX": {
          "type": "double",
          "value": 1.0
        },
        "translateY": {
          "type": "doubleLinear",
          "value": 0.0
        },
        "rotateZ": {
          "type": "doubleAngle",
          "value": 0.0
        },
        "scaleZ": {
          "type": "double",
          "value": 1.0
        },
        "rotateY": {
          "type": "doubleAngle",
          "value": 0.0
        }
      }
    },
    "RollToes_L": {
      "attrs": {
        "rotateX": {
          "type": "doubleAngle",
          "value": 0.0
        },
        "translateZ": {
          "type": "doubleLinear",
          "value": 0.0
        },
        "scaleY": {
          "type": "double",
          "value": 1.0
        },
        "translateX": {
          "type": "doubleLinear",
          "value": 0.0
        },
        "scaleX": {
          "type": "double",
          "value": 1.0
        },
        "translateY": {
          "type": "doubleLinear",
          "value": 0.0
        },
        "rotateZ": {
          "type": "doubleAngle",
          "value": 0.0
        },
        "scaleZ": {
          "type": "double",
          "value": 1.0
        },
        "rotateY": {
          "type": "doubleAngle",
          "value": 0.0
        }
      }
    },
    "FKIKLeg_L": {
      "attrs": {
        "IKVis": {
          "type": "bool",
          "value": true
        },
        "FKIKBlend": {
          "type": "double",
          "value": 10.0
        },
        "FKVis": {
          "type": "bool",
          "value": true
        }
      }
    },
    "FKPinkyFinger2_L": {
      "attrs": {
        "rotateX": {
          "type": "doubleAngle",
          "value": 0.0
        },
        "translateZ": {
          "type": "doubleLinear",
          "value": 0.0
        },
        "scaleY": {
          "type": "double",
          "value": 1.0
        },
        "translateX": {
          "type": "doubleLinear",
          "value": 0.0
        },
        "scaleX": {
          "type": "double",
          "value": 1.0
        },
        "translateY": {
          "type": "doubleLinear",
          "value": 0.0
        },
        "rotateZ": {
          "type": "doubleAngle",
          "value": 0.0
        },
        "scaleZ": {
          "type": "double",
          "value": 1.0
        },
        "rotateY": {
          "type": "doubleAngle",
          "value": 0.0
        }
      }
    },
    "FKPinkyFinger0_L": {
      "attrs": {
        "rotateX": {
          "type": "doubleAngle",
          "value": 0.0
        },
        "translateZ": {
          "type": "doubleLinear",
          "value": 0.0
        },
        "scaleY": {
          "type": "double",
          "value": 1.0
        },
        "translateX": {
          "type": "doubleLinear",
          "value": 0.0
        },
        "scaleX": {
          "type": "double",
          "value": 1.0
        },
        "translateY": {
          "type": "doubleLinear",
          "value": 0.0
        },
        "rotateZ": {
          "type": "doubleAngle",
          "value": 0.0
        },
        "scaleZ": {
          "type": "double",
          "value": 1.0
        },
        "rotateY": {
          "type": "doubleAngle",
          "value": 0.0
        }
      }
    },
    "FKIndexFinger1_R": {
      "attrs": {
        "rotateX": {
          "type": "doubleAngle",
          "value": 0.0
        },
        "translateZ": {
          "type": "doubleLinear",
          "value": 0.0
        },
        "scaleY": {
          "type": "double",
          "value": 1.0
        },
        "translateX": {
          "type": "doubleLinear",
          "value": 0.0
        },
        "scaleX": {
          "type": "double",
          "value": 1.0
        },
        "translateY": {
          "type": "doubleLinear",
          "value": 0.0
        },
        "rotateZ": {
          "type": "doubleAngle",
          "value": 0.0
        },
        "scaleZ": {
          "type": "double",
          "value": 1.0
        },
        "rotateY": {
          "type": "doubleAngle",
          "value": 0.0
        }
      }
    },
    "FKMiddleFinger2_R": {
      "attrs": {
        "rotateX": {
          "type": "doubleAngle",
          "value": 0.0
        },
        "translateZ": {
          "type": "doubleLinear",
          "value": 0.0
        },
        "scaleY": {
          "type": "double",
          "value": 1.0
        },
        "translateX": {
          "type": "doubleLinear",
          "value": 0.0
        },
        "scaleX": {
          "type": "double",
          "value": 1.0
        },
        "translateY": {
          "type": "doubleLinear",
          "value": 0.0
        },
        "rotateZ": {
          "type": "doubleAngle",
          "value": 0.0
        },
        "scaleZ": {
          "type": "double",
          "value": 1.0
        },
        "rotateY": {
          "type": "doubleAngle",
          "value": 0.0
        }
      }
    },
    "FKRingFinger1_R": {
      "attrs": {
        "rotateX": {
          "type": "doubleAngle",
          "value": 0.0
        },
        "translateZ": {
          "type": "doubleLinear",
          "value": 0.0
        },
        "scaleY": {
          "type": "double",
          "value": 1.0
        },
        "translateX": {
          "type": "doubleLinear",
          "value": 0.0
        },
        "scaleX": {
          "type": "double",
          "value": 1.0
        },
        "translateY": {
          "type": "doubleLinear",
          "value": 0.0
        },
        "rotateZ": {
          "type": "doubleAngle",
          "value": 0.0
        },
        "scaleZ": {
          "type": "double",
          "value": 1.0
        },
        "rotateY": {
          "type": "doubleAngle",
          "value": 0.0
        }
      }
    },
    "FKPinkyFinger1_R": {
      "attrs": {
        "rotateX": {
          "type": "doubleAngle",
          "value": 0.0
        },
        "translateZ": {
          "type": "doubleLinear",
          "value": 0.0
        },
        "scaleY": {
          "type": "double",
          "value": 1.0
        },
        "translateX": {
          "type": "doubleLinear",
          "value": 0.0
        },
        "scaleX": {
          "type": "double",
          "value": 1.0
        },
        "translateY": {
          "type": "doubleLinear",
          "value": 0.0
        },
        "rotateZ": {
          "type": "doubleAngle",
          "value": 0.0
        },
        "scaleZ": {
          "type": "double",
          "value": 1.0
        },
        "rotateY": {
          "type": "doubleAngle",
          "value": 0.0
        }
      }
    },
    "IKSpine3_M": {
      "attrs": {
        "rotateX": {
          "type": "doubleAngle",
          "value": 0.0
        },
        "stiff": {
          "type": "double",
          "value": 7.9
        },
        "translateZ": {
          "type": "doubleLinear",
          "value": 0.0
        },
        "volume": {
          "type": "double",
          "value": 10.0
        },
        "scaleY": {
          "type": "double",
          "value": 1.0
        },
        "stretchy": {
          "type": "double",
          "value": 0.0
        },
        "translateX": {
          "type": "doubleLinear",
          "value": 0.0
        },
        "scaleX": {
          "type": "double",
          "value": 1.0
        },
        "translateY": {
          "type": "doubleLinear",
          "value": 0.0
        },
        "rotateZ": {
          "type": "doubleAngle",
          "value": 0.0
        },
        "follow": {
          "type": "double",
          "value": 5.9
        },
        "scaleZ": {
          "type": "double",
          "value": 1.0
        },
        "rotateY": {
          "type": "doubleAngle",
          "value": 0.0
        }
      }
    },
    "Main": {
      "attrs": {
        "visibility": {
          "type": "bool",
          "value": true
        },
        "translateZ": {
          "type": "doubleLinear",
          "value": 0.0
        },
        "scaleY": {
          "type": "double",
          "value": 1.0
        },
        "translateX": {
          "type": "doubleLinear",
          "value": 0.0
        },
        "scaleX": {
          "type": "double",
          "value": 1.0
        },
        "translateY": {
          "type": "doubleLinear",
          "value": 0.0
        },
        "rotateZ": {
          "type": "doubleAngle",
          "value": 0.0
        },
        "scaleZ": {
          "type": "double",
          "value": 1.0
        },
        "rotateY": {
          "type": "doubleAngle",
          "value": 0.0
        },
        "rotateX": {
          "type": "doubleAngle",
          "value": 0.0
        }
      }
    },
    "FKPinkyFinger2_R": {
      "attrs": {
        "rotateX": {
          "type": "doubleAngle",
          "value": 0.0
        },
        "translateZ": {
          "type": "doubleLinear",
          "value": 0.0
        },
        "scaleY": {
          "type": "double",
          "value": 1.0
        },
        "translateX": {
          "type": "doubleLinear",
          "value": 0.0
        },
        "scaleX": {
          "type": "double",
          "value": 1.0
        },
        "translateY": {
          "type": "doubleLinear",
          "value": 0.0
        },
        "rotateZ": {
          "type": "doubleAngle",
          "value": 0.0
        },
        "scaleZ": {
          "type": "double",
          "value": 1.0
        },
        "rotateY": {
          "type": "doubleAngle",
          "value": 0.0
        }
      }
    },
    "IKLeg_R": {
      "attrs": {
        "rock": {
          "type": "double",
          "value": 0.0
        },
        "Lenght2": {
          "type": "double",
          "value": 1.0
        },
        "stretchy": {
          "type": "double",
          "value": 0.0
        },
        "Fatness1": {
          "type": "double",
          "value": 0.0
        },
        "scaleX": {
          "type": "double",
          "value": 1.0
        },
        "Lenght1": {
          "type": "double",
          "value": 1.0
        },
        "rollEndAngle": {
          "type": "double",
          "value": 60.0
        },
        "rotateY": {
          "type": "doubleAngle",
          "value": 0.0
        },
        "Fatness2": {
          "type": "double",
          "value": 0.0
        },
        "roll": {
          "type": "double",
          "value": 0.0
        },
        "rollStartAngle": {
          "type": "double",
          "value": 30.0
        },
        "translateX": {
          "type": "doubleLinear",
          "value": 0.0
        },
        "translateY": {
          "type": "doubleLinear",
          "value": 0.0
        },
        "rotateZ": {
          "type": "doubleAngle",
          "value": 0.0
        },
        "scaleZ": {
          "type": "double",
          "value": 1.0
        },
        "rotateX": {
          "type": "doubleAngle",
          "value": 0.0
        },
        "antiPop": {
          "type": "double",
          "value": 0.0
        },
        "translateZ": {
          "type": "doubleLinear",
          "value": 0.0
        },
        "volume": {
          "type": "double",
          "value": 10.0
        },
        "scaleY": {
          "type": "double",
          "value": 1.0
        },
        "swivel": {
          "type": "double",
          "value": 0.0
        }
      }
    },
    "FKRingFinger2_L": {
      "attrs": {
        "rotateX": {
          "type": "doubleAngle",
          "value": 0.0
        },
        "translateZ": {
          "type": "doubleLinear",
          "value": 0.0
        },
        "scaleY": {
          "type": "double",
          "value": 1.0
        },
        "translateX": {
          "type": "doubleLinear",
          "value": 0.0
        },
        "scaleX": {
          "type": "double",
          "value": 1.0
        },
        "translateY": {
          "type": "doubleLinear",
          "value": 0.0
        },
        "rotateZ": {
          "type": "doubleAngle",
          "value": 0.0
        },
        "scaleZ": {
          "type": "double",
          "value": 1.0
        },
        "rotateY": {
          "type": "doubleAngle",
          "value": 0.0
        }
      }
    },
    "FKIKArm_L": {
      "attrs": {
        "IKVis": {
          "type": "bool",
          "value": true
        },
        "FKIKBlend": {
          "type": "double",
          "value": 10.0
        },
        "FKVis": {
          "type": "bool",
          "value": true
        }
      }
    },
    "FKScapula_R": {
      "attrs": {
        "rotateX": {
          "type": "doubleAngle",
          "value": 0.0
        },
        "translateZ": {
          "type": "doubleLinear",
          "value": 0.0
        },
        "scaleY": {
          "type": "double",
          "value": 1.0
        },
        "translateX": {
          "type": "doubleLinear",
          "value": 0.0
        },
        "scaleX": {
          "type": "double",
          "value": 1.0
        },
        "translateY": {
          "type": "doubleLinear",
          "value": 0.0
        },
        "rotateZ": {
          "type": "doubleAngle",
          "value": 0.0
        },
        "scaleZ": {
          "type": "double",
          "value": 1.0
        },
        "rotateY": {
          "type": "doubleAngle",
          "value": 0.0
        }
      }
    },
    "FKThumbFinger3_L": {
      "attrs": {
        "rotateX": {
          "type": "doubleAngle",
          "value": 0.0
        },
        "translateZ": {
          "type": "doubleLinear",
          "value": 0.0
        },
        "scaleY": {
          "type": "double",
          "value": 1.0
        },
        "translateX": {
          "type": "doubleLinear",
          "value": 0.0
        },
        "scaleX": {
          "type": "double",
          "value": 1.0
        },
        "translateY": {
          "type": "doubleLinear",
          "value": 0.0
        },
        "rotateZ": {
          "type": "doubleAngle",
          "value": 0.0
        },
        "scaleZ": {
          "type": "double",
          "value": 1.0
        },
        "rotateY": {
          "type": "doubleAngle",
          "value": 0.0
        }
      }
    },
    "IKArm_L": {
      "attrs": {
        "rotateX": {
          "type": "doubleAngle",
          "value": 0.0
        },
        "Fatness1": {
          "type": "double",
          "value": 0.0
        },
        "antiPop": {
          "type": "double",
          "value": 0.0
        },
        "translateZ": {
          "type": "doubleLinear",
          "value": 0.0
        },
        "volume": {
          "type": "double",
          "value": 10.0
        },
        "scaleY": {
          "type": "double",
          "value": 1.0
        },
        "Fatness2": {
          "type": "double",
          "value": 0.0
        },
        "stretchy": {
          "type": "double",
          "value": 0.0
        },
        "translateX": {
          "type": "doubleLinear",
          "value": 0.0
        },
        "scaleX": {
          "type": "double",
          "value": 1.0
        },
        "Lenght2": {
          "type": "double",
          "value": 1.0
        },
        "translateY": {
          "type": "doubleLinear",
          "value": 0.0
        },
        "rotateZ": {
          "type": "doubleAngle",
          "value": 0.0
        },
        "follow": {
          "type": "double",
          "value": 0.0
        },
        "scaleZ": {
          "type": "double",
          "value": 1.0
        },
        "Lenght1": {
          "type": "double",
          "value": 1.0
        },
        "rotateY": {
          "type": "doubleAngle",
          "value": 0.0
        }
      }
    },
    "FKMiddleFinger0_R": {
      "attrs": {
        "rotateX": {
          "type": "doubleAngle",
          "value": 0.0
        },
        "translateZ": {
          "type": "doubleLinear",
          "value": 0.0
        },
        "scaleY": {
          "type": "double",
          "value": 1.0
        },
        "translateX": {
          "type": "doubleLinear",
          "value": 0.0
        },
        "scaleX": {
          "type": "double",
          "value": 1.0
        },
        "translateY": {
          "type": "doubleLinear",
          "value": 0.0
        },
        "rotateZ": {
          "type": "doubleAngle",
          "value": 0.0
        },
        "scaleZ": {
          "type": "double",
          "value": 1.0
        },
        "rotateY": {
          "type": "doubleAngle",
          "value": 0.0
        }
      }
    },
    "RootX_M": {
      "attrs": {
        "visibility": {
          "type": "bool",
          "value": true
        },
        "translateZ": {
          "type": "doubleLinear",
          "value": 0.0
        },
        "translateX": {
          "type": "doubleLinear",
          "value": 0.0
        },
        "translateY": {
          "type": "doubleLinear",
          "value": 0.0
        },
        "rotateZ": {
          "type": "doubleAngle",
          "value": 0.0
        },
        "rotateY": {
          "type": "doubleAngle",
          "value": 0.0
        },
        "rotateX": {
          "type": "doubleAngle",
          "value": 0.0
        }
      }
    },
    "FKRingFinger2_R": {
      "attrs": {
        "rotateX": {
          "type": "doubleAngle",
          "value": 0.0
        },
        "translateZ": {
          "type": "doubleLinear",
          "value": 0.0
        },
        "scaleY": {
          "type": "double",
          "value": 1.0
        },
        "translateX": {
          "type": "doubleLinear",
          "value": 0.0
        },
        "scaleX": {
          "type": "double",
          "value": 1.0
        },
        "translateY": {
          "type": "doubleLinear",
          "value": 0.0
        },
        "rotateZ": {
          "type": "doubleAngle",
          "value": 0.0
        },
        "scaleZ": {
          "type": "double",
          "value": 1.0
        },
        "rotateY": {
          "type": "doubleAngle",
          "value": 0.0
        }
      }
    },
    "IKhybridSpine2_M": {
      "attrs": {
        "rotateX": {
          "type": "doubleAngle",
          "value": 0.0
        },
        "translateZ": {
          "type": "doubleLinear",
          "value": 0.0
        },
        "scaleY": {
          "type": "double",
          "value": 1.0
        },
        "translateX": {
          "type": "doubleLinear",
          "value": 0.0
        },
        "scaleX": {
          "type": "double",
          "value": 1.0
        },
        "translateY": {
          "type": "doubleLinear",
          "value": 0.0
        },
        "rotateZ": {
          "type": "doubleAngle",
          "value": 0.0
        },
        "scaleZ": {
          "type": "double",
          "value": 1.0
        },
        "rotateY": {
          "type": "doubleAngle",
          "value": 0.0
        }
      }
    },
    "FKMiddleFinger1_R": {
      "attrs": {
        "rotateX": {
          "type": "doubleAngle",
          "value": 0.0
        },
        "translateZ": {
          "type": "doubleLinear",
          "value": 0.0
        },
        "scaleY": {
          "type": "double",
          "value": 1.0
        },
        "translateX": {
          "type": "doubleLinear",
          "value": 0.0
        },
        "scaleX": {
          "type": "double",
          "value": 1.0
        },
        "translateY": {
          "type": "doubleLinear",
          "value": 0.0
        },
        "rotateZ": {
          "type": "doubleAngle",
          "value": 0.0
        },
        "scaleZ": {
          "type": "double",
          "value": 1.0
        },
        "rotateY": {
          "type": "doubleAngle",
          "value": 0.0
        }
      }
    },
    "FKMiddleFinger0_L": {
      "attrs": {
        "rotateX": {
          "type": "doubleAngle",
          "value": 0.0
        },
        "translateZ": {
          "type": "doubleLinear",
          "value": 0.0
        },
        "scaleY": {
          "type": "double",
          "value": 1.0
        },
        "translateX": {
          "type": "doubleLinear",
          "value": 0.0
        },
        "scaleX": {
          "type": "double",
          "value": 1.0
        },
        "translateY": {
          "type": "doubleLinear",
          "value": 0.0
        },
        "rotateZ": {
          "type": "doubleAngle",
          "value": 0.0
        },
        "scaleZ": {
          "type": "double",
          "value": 1.0
        },
        "rotateY": {
          "type": "doubleAngle",
          "value": 0.0
        }
      }
    },
    "RollToes_R": {
      "attrs": {
        "rotateX": {
          "type": "doubleAngle",
          "value": 0.0
        },
        "translateZ": {
          "type": "doubleLinear",
          "value": 0.0
        },
        "scaleY": {
          "type": "double",
          "value": 1.0
        },
        "translateX": {
          "type": "doubleLinear",
          "value": 0.0
        },
        "scaleX": {
          "type": "double",
          "value": 1.0
        },
        "translateY": {
          "type": "doubleLinear",
          "value": 0.0
        },
        "rotateZ": {
          "type": "doubleAngle",
          "value": 0.0
        },
        "scaleZ": {
          "type": "double",
          "value": 1.0
        },
        "rotateY": {
          "type": "doubleAngle",
          "value": 0.0
        }
      }
    },
    "Fingers_R": {
      "attrs": {
        "spread": {
          "type": "float",
          "value": 0.0
        },
        "pinkyCurl": {
          "type": "float",
          "value": 2.3267033100128174
        },
        "ringCurl": {
          "type": "float",
          "value": 2.22670316696167
        },
        "indexCurl": {
          "type": "float",
          "value": 0.6267032623291016
        },
        "thumbCurl": {
          "type": "float",
          "value": 0.3999999761581421
        },
        "middleCurl": {
          "type": "float",
          "value": 1.3267033100128174
        }
      }
    },
    "FKRingFinger0_R": {
      "attrs": {
        "rotateX": {
          "type": "doubleAngle",
          "value": 0.0
        },
        "translateZ": {
          "type": "doubleLinear",
          "value": 0.0
        },
        "scaleY": {
          "type": "double",
          "value": 1.0
        },
        "translateX": {
          "type": "doubleLinear",
          "value": 0.0
        },
        "scaleX": {
          "type": "double",
          "value": 1.0
        },
        "translateY": {
          "type": "doubleLinear",
          "value": 0.0
        },
        "rotateZ": {
          "type": "doubleAngle",
          "value": 0.0
        },
        "scaleZ": {
          "type": "double",
          "value": 1.0
        },
        "rotateY": {
          "type": "doubleAngle",
          "value": 0.0
        }
      }
    },
    "FKMiddleFinger3_R": {
      "attrs": {
        "rotateX": {
          "type": "doubleAngle",
          "value": 0.0
        },
        "translateZ": {
          "type": "doubleLinear",
          "value": 0.0
        },
        "scaleY": {
          "type": "double",
          "value": 1.0
        },
        "translateX": {
          "type": "doubleLinear",
          "value": 0.0
        },
        "scaleX": {
          "type": "double",
          "value": 1.0
        },
        "translateY": {
          "type": "doubleLinear",
          "value": 0.0
        },
        "rotateZ": {
          "type": "doubleAngle",
          "value": 0.0
        },
        "scaleZ": {
          "type": "double",
          "value": 1.0
        },
        "rotateY": {
          "type": "doubleAngle",
          "value": 0.0
        }
      }
    },
    "PoleArm_L": {
      "attrs": {
        "translateZ": {
          "type": "doubleLinear",
          "value": 0.0
        },
        "translateX": {
          "type": "doubleLinear",
          "value": 0.0
        },
        "lock": {
          "type": "double",
          "value": 0.0
        },
        "translateY": {
          "type": "doubleLinear",
          "value": 0.0
        },
        "follow": {
          "type": "double",
          "value": 0.0
        }
      }
    },
    "IKToes_L": {
      "attrs": {
        "rotateX": {
          "type": "doubleAngle",
          "value": 0.0
        },
        "translateZ": {
          "type": "doubleLinear",
          "value": 0.0
        },
        "scaleY": {
          "type": "double",
          "value": 1.0
        },
        "translateX": {
          "type": "doubleLinear",
          "value": 0.0
        },
        "scaleX": {
          "type": "double",
          "value": 1.0
        },
        "translateY": {
          "type": "doubleLinear",
          "value": 0.0
        },
        "rotateZ": {
          "type": "doubleAngle",
          "value": 0.0
        },
        "scaleZ": {
          "type": "double",
          "value": 1.0
        },
        "rotateY": {
          "type": "doubleAngle",
          "value": 0.0
        }
      }
    },
    "FKIndexFinger3_R": {
      "attrs": {
        "rotateX": {
          "type": "doubleAngle",
          "value": 0.0
        },
        "translateZ": {
          "type": "doubleLinear",
          "value": 0.0
        },
        "scaleY": {
          "type": "double",
          "value": 1.0
        },
        "translateX": {
          "type": "doubleLinear",
          "value": 0.0
        },
        "scaleX": {
          "type": "double",
          "value": 1.0
        },
        "translateY": {
          "type": "doubleLinear",
          "value": 0.0
        },
        "rotateZ": {
          "type": "doubleAngle",
          "value": 0.0
        },
        "scaleZ": {
          "type": "double",
          "value": 1.0
        },
        "rotateY": {
          "type": "doubleAngle",
          "value": 0.0
        }
      }
    },
    "FKIndexFinger2_R": {
      "attrs": {
        "rotateX": {
          "type": "doubleAngle",
          "value": 0.0
        },
        "translateZ": {
          "type": "doubleLinear",
          "value": 0.0
        },
        "scaleY": {
          "type": "double",
          "value": 1.0
        },
        "translateX": {
          "type": "doubleLinear",
          "value": 0.0
        },
        "scaleX": {
          "type": "double",
          "value": 1.0
        },
        "translateY": {
          "type": "doubleLinear",
          "value": 0.0
        },
        "rotateZ": {
          "type": "doubleAngle",
          "value": 0.0
        },
        "scaleZ": {
          "type": "double",
          "value": 1.0
        },
        "rotateY": {
          "type": "doubleAngle",
          "value": 0.0
        }
      }
    },
    "FKScapula_L": {
      "attrs": {
        "rotateX": {
          "type": "doubleAngle",
          "value": 0.0
        },
        "translateZ": {
          "type": "doubleLinear",
          "value": 0.0
        },
        "scaleY": {
          "type": "double",
          "value": 1.0
        },
        "translateX": {
          "type": "doubleLinear",
          "value": 0.0
        },
        "scaleX": {
          "type": "double",
          "value": 1.0
        },
        "translateY": {
          "type": "doubleLinear",
          "value": 0.0
        },
        "rotateZ": {
          "type": "doubleAngle",
          "value": 0.0
        },
        "scaleZ": {
          "type": "double",
          "value": 1.0
        },
        "rotateY": {
          "type": "doubleAngle",
          "value": 0.0
        }
      }
    },
    "RollHeel_L": {
      "attrs": {
        "rotateX": {
          "type": "doubleAngle",
          "value": 0.0
        },
        "translateZ": {
          "type": "doubleLinear",
          "value": 0.0
        },
        "scaleY": {
          "type": "double",
          "value": 1.0
        },
        "translateX": {
          "type": "doubleLinear",
          "value": 0.0
        },
        "scaleX": {
          "type": "double",
          "value": 1.0
        },
        "translateY": {
          "type": "doubleLinear",
          "value": 0.0
        },
        "rotateZ": {
          "type": "doubleAngle",
          "value": 0.0
        },
        "scaleZ": {
          "type": "double",
          "value": 1.0
        },
        "rotateY": {
          "type": "doubleAngle",
          "value": 0.0
        }
      }
    },
    "IKArm_R": {
      "attrs": {
        "rotateX": {
          "type": "doubleAngle",
          "value": 0.0
        },
        "Fatness1": {
          "type": "double",
          "value": 0.0
        },
        "antiPop": {
          "type": "double",
          "value": 0.0
        },
        "translateZ": {
          "type": "doubleLinear",
          "value": 0.0
        },
        "volume": {
          "type": "double",
          "value": 10.0
        },
        "scaleY": {
          "type": "double",
          "value": 1.0
        },
        "Fatness2": {
          "type": "double",
          "value": 0.0
        },
        "stretchy": {
          "type": "double",
          "value": 0.0
        },
        "translateX": {
          "type": "doubleLinear",
          "value": 0.0
        },
        "scaleX": {
          "type": "double",
          "value": 1.0
        },
        "Lenght2": {
          "type": "double",
          "value": 1.0
        },
        "translateY": {
          "type": "doubleLinear",
          "value": 0.0
        },
        "rotateZ": {
          "type": "doubleAngle",
          "value": 0.0
        },
        "follow": {
          "type": "double",
          "value": 0.0
        },
        "scaleZ": {
          "type": "double",
          "value": 1.0
        },
        "Lenght1": {
          "type": "double",
          "value": 1.0
        },
        "rotateY": {
          "type": "doubleAngle",
          "value": 0.0
        }
      }
    },
    "FKNeck_M": {
      "attrs": {
        "rotateX": {
          "type": "doubleAngle",
          "value": 0.0
        },
        "translateZ": {
          "type": "doubleLinear",
          "value": 0.0
        },
        "scaleY": {
          "type": "double",
          "value": 1.0
        },
        "translateX": {
          "type": "doubleLinear",
          "value": 0.0
        },
        "scaleX": {
          "type": "double",
          "value": 1.0
        },
        "translateY": {
          "type": "doubleLinear",
          "value": 0.0
        },
        "rotateZ": {
          "type": "doubleAngle",
          "value": 0.0
        },
        "scaleZ": {
          "type": "double",
          "value": 1.0
        },
        "rotateY": {
          "type": "doubleAngle",
          "value": 0.0
        }
      }
    },
    "FKIKArm_R": {
      "attrs": {
        "IKVis": {
          "type": "bool",
          "value": true
        },
        "FKIKBlend": {
          "type": "double",
          "value": 10.0
        },
        "FKVis": {
          "type": "bool",
          "value": true
        }
      }
    },
    "Fingers_L": {
      "attrs": {
        "spread": {
          "type": "float",
          "value": 0.0
        },
        "pinkyCurl": {
          "type": "float",
          "value": 2.726703405380249
        },
        "ringCurl": {
          "type": "float",
          "value": 2.026703357696533
        },
        "indexCurl": {
          "type": "float",
          "value": 1.0267033576965332
        },
        "thumbCurl": {
          "type": "float",
          "value": 1.0
        },
        "middleCurl": {
          "type": "float",
          "value": 1.3267031908035278
        }
      }
    },
    "FKIndexFinger2_L": {
      "attrs": {
        "rotateX": {
          "type": "doubleAngle",
          "value": 0.0
        },
        "translateZ": {
          "type": "doubleLinear",
          "value": 0.0
        },
        "scaleY": {
          "type": "double",
          "value": 1.0
        },
        "translateX": {
          "type": "doubleLinear",
          "value": 0.0
        },
        "scaleX": {
          "type": "double",
          "value": 1.0
        },
        "translateY": {
          "type": "doubleLinear",
          "value": 0.0
        },
        "rotateZ": {
          "type": "doubleAngle",
          "value": 0.0
        },
        "scaleZ": {
          "type": "double",
          "value": 1.0
        },
        "rotateY": {
          "type": "doubleAngle",
          "value": 0.0
        }
      }
    },
    "IKSpine2_M": {
      "attrs": {
        "rotateX": {
          "type": "doubleAngle",
          "value": 0.0
        },
        "followEnd": {
          "type": "double",
          "value": 5.0
        },
        "translateZ": {
          "type": "doubleLinear",
          "value": 0.0
        },
        "scaleY": {
          "type": "double",
          "value": 1.0
        },
        "translateX": {
          "type": "doubleLinear",
          "value": 0.0
        },
        "scaleX": {
          "type": "double",
          "value": 1.0
        },
        "translateY": {
          "type": "doubleLinear",
          "value": 0.0
        },
        "rotateZ": {
          "type": "doubleAngle",
          "value": 0.0
        },
        "scaleZ": {
          "type": "double",
          "value": 1.0
        },
        "rotateY": {
          "type": "doubleAngle",
          "value": 0.0
        }
      }
    },
    "FKJaw_M": {
      "attrs": {
        "rotateX": {
          "type": "doubleAngle",
          "value": 0.0
        },
        "translateZ": {
          "type": "doubleLinear",
          "value": 0.0
        },
        "scaleY": {
          "type": "double",
          "value": 1.0
        },
        "translateX": {
          "type": "doubleLinear",
          "value": 0.0
        },
        "scaleX": {
          "type": "double",
          "value": 1.0
        },
        "translateY": {
          "type": "doubleLinear",
          "value": 0.0
        },
        "rotateZ": {
          "type": "doubleAngle",
          "value": 0.0
        },
        "scaleZ": {
          "type": "double",
          "value": 1.0
        },
        "rotateY": {
          "type": "doubleAngle",
          "value": 0.0
        }
      }
    },
    "FKThumbFinger2_L": {
      "attrs": {
        "rotateX": {
          "type": "doubleAngle",
          "value": 0.0
        },
        "translateZ": {
          "type": "doubleLinear",
          "value": 0.0
        },
        "scaleY": {
          "type": "double",
          "value": 1.0
        },
        "translateX": {
          "type": "doubleLinear",
          "value": 0.0
        },
        "scaleX": {
          "type": "double",
          "value": 1.0
        },
        "translateY": {
          "type": "doubleLinear",
          "value": 0.0
        },
        "rotateZ": {
          "type": "doubleAngle",
          "value": 0.0
        },
        "scaleZ": {
          "type": "double",
          "value": 1.0
        },
        "rotateY": {
          "type": "doubleAngle",
          "value": 0.0
        }
      }
    },
    "PoleLeg_L": {
      "attrs": {
        "translateZ": {
          "type": "doubleLinear",
          "value": 0.0
        },
        "translateX": {
          "type": "doubleLinear",
          "value": 0.0
        },
        "lock": {
          "type": "double",
          "value": 0.0
        },
        "translateY": {
          "type": "doubleLinear",
          "value": 0.0
        },
        "follow": {
          "type": "double",
          "value": 10.0
        }
      }
    },
    "IKLeg_L": {
      "attrs": {
        "rock": {
          "type": "double",
          "value": 0.0
        },
        "Lenght2": {
          "type": "double",
          "value": 1.0
        },
        "stretchy": {
          "type": "double",
          "value": 0.0
        },
        "Fatness1": {
          "type": "double",
          "value": 0.0
        },
        "scaleX": {
          "type": "double",
          "value": 1.0
        },
        "Lenght1": {
          "type": "double",
          "value": 1.0
        },
        "rollEndAngle": {
          "type": "double",
          "value": 60.0
        },
        "rotateY": {
          "type": "doubleAngle",
          "value": 0.0
        },
        "Fatness2": {
          "type": "double",
          "value": 0.0
        },
        "roll": {
          "type": "double",
          "value": 0.0
        },
        "rollStartAngle": {
          "type": "double",
          "value": 30.0
        },
        "translateX": {
          "type": "doubleLinear",
          "value": 0.0
        },
        "translateY": {
          "type": "doubleLinear",
          "value": 0.0
        },
        "rotateZ": {
          "type": "doubleAngle",
          "value": 0.0
        },
        "scaleZ": {
          "type": "double",
          "value": 1.0
        },
        "rotateX": {
          "type": "doubleAngle",
          "value": 0.0
        },
        "antiPop": {
          "type": "double",
          "value": 0.0
        },
        "translateZ": {
          "type": "doubleLinear",
          "value": 0.0
        },
        "volume": {
          "type": "double",
          "value": 10.0
        },
        "scaleY": {
          "type": "double",
          "value": 1.0
        },
        "swivel": {
          "type": "double",
          "value": 0.0
        }
      }
    },
    "FKPinkyFinger3_L": {
      "attrs": {
        "rotateX": {
          "type": "doubleAngle",
          "value": 0.0
        },
        "translateZ": {
          "type": "doubleLinear",
          "value": 0.0
        },
        "scaleY": {
          "type": "double",
          "value": 1.0
        },
        "translateX": {
          "type": "doubleLinear",
          "value": 0.0
        },
        "scaleX": {
          "type": "double",
          "value": 1.0
        },
        "translateY": {
          "type": "doubleLinear",
          "value": 0.0
        },
        "rotateZ": {
          "type": "doubleAngle",
          "value": 0.0
        },
        "scaleZ": {
          "type": "double",
          "value": 1.0
        },
        "rotateY": {
          "type": "doubleAngle",
          "value": 0.0
        }
      }
    },
    "AimEye_L": {
      "attrs": {
        "translateY": {
          "type": "doubleLinear",
          "value": 0.0
        },
        "translateZ": {
          "type": "doubleLinear",
          "value": 0.0
        },
        "translateX": {
          "type": "doubleLinear",
          "value": 0.0
        }
      }
    },
    "FKRingFinger3_L": {
      "attrs": {
        "rotateX": {
          "type": "doubleAngle",
          "value": 0.0
        },
        "translateZ": {
          "type": "doubleLinear",
          "value": 0.0
        },
        "scaleY": {
          "type": "double",
          "value": 1.0
        },
        "translateX": {
          "type": "doubleLinear",
          "value": 0.0
        },
        "scaleX": {
          "type": "double",
          "value": 1.0
        },
        "translateY": {
          "type": "doubleLinear",
          "value": 0.0
        },
        "rotateZ": {
          "type": "doubleAngle",
          "value": 0.0
        },
        "scaleZ": {
          "type": "double",
          "value": 1.0
        },
        "rotateY": {
          "type": "doubleAngle",
          "value": 0.0
        }
      }
    },
    "FKThumbFinger1_R": {
      "attrs": {
        "rotateX": {
          "type": "doubleAngle",
          "value": 0.0
        },
        "translateZ": {
          "type": "doubleLinear",
          "value": 0.0
        },
        "scaleY": {
          "type": "double",
          "value": 1.0
        },
        "translateX": {
          "type": "doubleLinear",
          "value": 0.0
        },
        "scaleX": {
          "type": "double",
          "value": 1.0
        },
        "translateY": {
          "type": "doubleLinear",
          "value": 0.0
        },
        "rotateZ": {
          "type": "doubleAngle",
          "value": 0.0
        },
        "scaleZ": {
          "type": "double",
          "value": 1.0
        },
        "rotateY": {
          "type": "doubleAngle",
          "value": 0.0
        }
      }
    },
    "IKhybridSpine3_M": {
      "attrs": {
        "rotateX": {
          "type": "doubleAngle",
          "value": 0.0
        },
        "translateZ": {
          "type": "doubleLinear",
          "value": 0.0
        },
        "scaleY": {
          "type": "double",
          "value": 1.0
        },
        "translateX": {
          "type": "doubleLinear",
          "value": 0.0
        },
        "scaleX": {
          "type": "double",
          "value": 1.0
        },
        "translateY": {
          "type": "doubleLinear",
          "value": 0.0
        },
        "rotateZ": {
          "type": "doubleAngle",
          "value": 0.0
        },
        "scaleZ": {
          "type": "double",
          "value": 1.0
        },
        "rotateY": {
          "type": "doubleAngle",
          "value": 0.0
        }
      }
    },
    "FKRingFinger0_L": {
      "attrs": {
        "rotateX": {
          "type": "doubleAngle",
          "value": 0.0
        },
        "translateZ": {
          "type": "doubleLinear",
          "value": 0.0
        },
        "scaleY": {
          "type": "double",
          "value": 1.0
        },
        "translateX": {
          "type": "doubleLinear",
          "value": 0.0
        },
        "scaleX": {
          "type": "double",
          "value": 1.0
        },
        "translateY": {
          "type": "doubleLinear",
          "value": 0.0
        },
        "rotateZ": {
          "type": "doubleAngle",
          "value": 0.0
        },
        "scaleZ": {
          "type": "double",
          "value": 1.0
        },
        "rotateY": {
          "type": "doubleAngle",
          "value": 0.0
        }
      }
    },
    "FKIndexFinger0_R": {
      "attrs": {
        "rotateX": {
          "type": "doubleAngle",
          "value": 0.0
        },
        "translateZ": {
          "type": "doubleLinear",
          "value": 0.0
        },
        "scaleY": {
          "type": "double",
          "value": 1.0
        },
        "translateX": {
          "type": "doubleLinear",
          "value": 0.0
        },
        "scaleX": {
          "type": "double",
          "value": 1.0
        },
        "translateY": {
          "type": "doubleLinear",
          "value": 0.0
        },
        "rotateZ": {
          "type": "doubleAngle",
          "value": 0.0
        },
        "scaleZ": {
          "type": "double",
          "value": 1.0
        },
        "rotateY": {
          "type": "doubleAngle",
          "value": 0.0
        }
      }
    },
    "AimEye_R": {
      "attrs": {
        "translateY": {
          "type": "doubleLinear",
          "value": 0.0
        },
        "translateZ": {
          "type": "doubleLinear",
          "value": 0.0
        },
        "translateX": {
          "type": "doubleLinear",
          "value": 0.0
        }
      }
    },
    "FKMiddleFinger2_L": {
      "attrs": {
        "rotateX": {
          "type": "doubleAngle",
          "value": 0.0
        },
        "translateZ": {
          "type": "doubleLinear",
          "value": 0.0
        },
        "scaleY": {
          "type": "double",
          "value": 1.0
        },
        "translateX": {
          "type": "doubleLinear",
          "value": 0.0
        },
        "scaleX": {
          "type": "double",
          "value": 1.0
        },
        "translateY": {
          "type": "doubleLinear",
          "value": 0.0
        },
        "rotateZ": {
          "type": "doubleAngle",
          "value": 0.0
        },
        "scaleZ": {
          "type": "double",
          "value": 1.0
        },
        "rotateY": {
          "type": "doubleAngle",
          "value": 0.0
        }
      }
    },
    "FKRingFinger3_R": {
      "attrs": {
        "rotateX": {
          "type": "doubleAngle",
          "value": 0.0
        },
        "translateZ": {
          "type": "doubleLinear",
          "value": 0.0
        },
        "scaleY": {
          "type": "double",
          "value": 1.0
        },
        "translateX": {
          "type": "doubleLinear",
          "value": 0.0
        },
        "scaleX": {
          "type": "double",
          "value": 1.0
        },
        "translateY": {
          "type": "doubleLinear",
          "value": 0.0
        },
        "rotateZ": {
          "type": "doubleAngle",
          "value": 0.0
        },
        "scaleZ": {
          "type": "double",
          "value": 1.0
        },
        "rotateY": {
          "type": "doubleAngle",
          "value": 0.0
        }
      }
    },
    "FKMiddleFinger1_L": {
      "attrs": {
        "rotateX": {
          "type": "doubleAngle",
          "value": 0.0
        },
        "translateZ": {
          "type": "doubleLinear",
          "value": 0.0
        },
        "scaleY": {
          "type": "double",
          "value": 1.0
        },
        "translateX": {
          "type": "doubleLinear",
          "value": 0.0
        },
        "scaleX": {
          "type": "double",
          "value": 1.0
        },
        "translateY": {
          "type": "doubleLinear",
          "value": 0.0
        },
        "rotateZ": {
          "type": "doubleAngle",
          "value": 0.0
        },
        "scaleZ": {
          "type": "double",
          "value": 1.0
        },
        "rotateY": {
          "type": "doubleAngle",
          "value": 0.0
        }
      }
    },
    "RollToesEnd_R": {
      "attrs": {
        "rotateX": {
          "type": "doubleAngle",
          "value": 0.0
        },
        "translateZ": {
          "type": "doubleLinear",
          "value": 0.0
        },
        "scaleY": {
          "type": "double",
          "value": 1.0
        },
        "translateX": {
          "type": "doubleLinear",
          "value": 0.0
        },
        "scaleX": {
          "type": "double",
          "value": 1.0
        },
        "translateY": {
          "type": "doubleLinear",
          "value": 0.0
        },
        "rotateZ": {
          "type": "doubleAngle",
          "value": 0.0
        },
        "scaleZ": {
          "type": "double",
          "value": 1.0
        },
        "rotateY": {
          "type": "doubleAngle",
          "value": 0.0
        }
      }
    },
    "FKEye_R": {
      "attrs": {
        "rotateX": {
          "type": "doubleAngle",
          "value": 0.0
        },
        "translateZ": {
          "type": "doubleLinear",
          "value": 0.0
        },
        "scaleY": {
          "type": "double",
          "value": 1.0
        },
        "translateX": {
          "type": "doubleLinear",
          "value": 0.0
        },
        "scaleX": {
          "type": "double",
          "value": 1.0
        },
        "translateY": {
          "type": "doubleLinear",
          "value": 0.0
        },
        "rotateZ": {
          "type": "doubleAngle",
          "value": 0.0
        },
        "scaleZ": {
          "type": "double",
          "value": 1.0
        },
        "rotateY": {
          "type": "doubleAngle",
          "value": 0.0
        }
      }
    },
    "RollHeel_R": {
      "attrs": {
        "rotateX": {
          "type": "doubleAngle",
          "value": 0.0
        },
        "translateZ": {
          "type": "doubleLinear",
          "value": 0.0
        },
        "scaleY": {
          "type": "double",
          "value": 1.0
        },
        "translateX": {
          "type": "doubleLinear",
          "value": 0.0
        },
        "scaleX": {
          "type": "double",
          "value": 1.0
        },
        "translateY": {
          "type": "doubleLinear",
          "value": 0.0
        },
        "rotateZ": {
          "type": "doubleAngle",
          "value": 0.0
        },
        "scaleZ": {
          "type": "double",
          "value": 1.0
        },
        "rotateY": {
          "type": "doubleAngle",
          "value": 0.0
        }
      }
    },
    "IKToes_R": {
      "attrs": {
        "rotateX": {
          "type": "doubleAngle",
          "value": 0.0
        },
        "translateZ": {
          "type": "doubleLinear",
          "value": 0.0
        },
        "scaleY": {
          "type": "double",
          "value": 1.0
        },
        "translateX": {
          "type": "doubleLinear",
          "value": 0.0
        },
        "scaleX": {
          "type": "double",
          "value": 1.0
        },
        "translateY": {
          "type": "doubleLinear",
          "value": 0.0
        },
        "rotateZ": {
          "type": "doubleAngle",
          "value": 0.0
        },
        "scaleZ": {
          "type": "double",
          "value": 1.0
        },
        "rotateY": {
          "type": "doubleAngle",
          "value": 0.0
        }
      }
    },
    "FKIndexFinger1_L": {
      "attrs": {
        "rotateX": {
          "type": "doubleAngle",
          "value": 0.0
        },
        "translateZ": {
          "type": "doubleLinear",
          "value": 0.0
        },
        "scaleY": {
          "type": "double",
          "value": 1.0
        },
        "translateX": {
          "type": "doubleLinear",
          "value": 0.0
        },
        "scaleX": {
          "type": "double",
          "value": 1.0
        },
        "translateY": {
          "type": "doubleLinear",
          "value": 0.0
        },
        "rotateZ": {
          "type": "doubleAngle",
          "value": 0.0
        },
        "scaleZ": {
          "type": "double",
          "value": 1.0
        },
        "rotateY": {
          "type": "doubleAngle",
          "value": 0.0
        }
      }
    },
    "PoleLeg_R": {
      "attrs": {
        "translateZ": {
          "type": "doubleLinear",
          "value": 0.0
        },
        "translateX": {
          "type": "doubleLinear",
          "value": 0.0
        },
        "lock": {
          "type": "double",
          "value": 0.0
        },
        "translateY": {
          "type": "doubleLinear",
          "value": 0.0
        },
        "follow": {
          "type": "double",
          "value": 10.0
        }
      }
    },
    "FKThumbFinger3_R": {
      "attrs": {
        "rotateX": {
          "type": "doubleAngle",
          "value": 0.0
        },
        "translateZ": {
          "type": "doubleLinear",
          "value": 0.0
        },
        "scaleY": {
          "type": "double",
          "value": 1.0
        },
        "translateX": {
          "type": "doubleLinear",
          "value": 0.0
        },
        "scaleX": {
          "type": "double",
          "value": 1.0
        },
        "translateY": {
          "type": "doubleLinear",
          "value": 0.0
        },
        "rotateZ": {
          "type": "doubleAngle",
          "value": 0.0
        },
        "scaleZ": {
          "type": "double",
          "value": 1.0
        },
        "rotateY": {
          "type": "doubleAngle",
          "value": 0.0
        }
      }
    },
    "FKRingFinger1_L": {
      "attrs": {
        "rotateX": {
          "type": "doubleAngle",
          "value": 0.0
        },
        "translateZ": {
          "type": "doubleLinear",
          "value": 0.0
        },
        "scaleY": {
          "type": "double",
          "value": 1.0
        },
        "translateX": {
          "type": "doubleLinear",
          "value": 0.0
        },
        "scaleX": {
          "type": "double",
          "value": 1.0
        },
        "translateY": {
          "type": "doubleLinear",
          "value": 0.0
        },
        "rotateZ": {
          "type": "doubleAngle",
          "value": 0.0
        },
        "scaleZ": {
          "type": "double",
          "value": 1.0
        },
        "rotateY": {
          "type": "doubleAngle",
          "value": 0.0
        }
      }
    },
    "FKPinkyFinger3_R": {
      "attrs": {
        "rotateX": {
          "type": "doubleAngle",
          "value": 0.0
        },
        "translateZ": {
          "type": "doubleLinear",
          "value": 0.0
        },
        "scaleY": {
          "type": "double",
          "value": 1.0
        },
        "translateX": {
          "type": "doubleLinear",
          "value": 0.0
        },
        "scaleX": {
          "type": "double",
          "value": 1.0
        },
        "translateY": {
          "type": "doubleLinear",
          "value": 0.0
        },
        "rotateZ": {
          "type": "doubleAngle",
          "value": 0.0
        },
        "scaleZ": {
          "type": "double",
          "value": 1.0
        },
        "rotateY": {
          "type": "doubleAngle",
          "value": 0.0
        }
      }
    },
    "FKIndexFinger0_L": {
      "attrs": {
        "rotateX": {
          "type": "doubleAngle",
          "value": 0.0
        },
        "translateZ": {
          "type": "doubleLinear",
          "value": 0.0
        },
        "scaleY": {
          "type": "double",
          "value": 1.0
        },
        "translateX": {
          "type": "doubleLinear",
          "value": 0.0
        },
        "scaleX": {
          "type": "double",
          "value": 1.0
        },
        "translateY": {
          "type": "doubleLinear",
          "value": 0.0
        },
        "rotateZ": {
          "type": "doubleAngle",
          "value": 0.0
        },
        "scaleZ": {
          "type": "double",
          "value": 1.0
        },
        "rotateY": {
          "type": "doubleAngle",
          "value": 0.0
        }
      }
    },
    "FKEye_L": {
      "attrs": {
        "rotateX": {
          "type": "doubleAngle",
          "value": 0.0
        },
        "translateZ": {
          "type": "doubleLinear",
          "value": 0.0
        },
        "scaleY": {
          "type": "double",
          "value": 1.0
        },
        "translateX": {
          "type": "doubleLinear",
          "value": 0.0
        },
        "scaleX": {
          "type": "double",
          "value": 1.0
        },
        "translateY": {
          "type": "doubleLinear",
          "value": 0.0
        },
        "rotateZ": {
          "type": "doubleAngle",
          "value": 0.0
        },
        "scaleZ": {
          "type": "double",
          "value": 1.0
        },
        "rotateY": {
          "type": "doubleAngle",
          "value": 0.0
        }
      }
    },
    "RollToesEnd_L": {
      "attrs": {
        "rotateX": {
          "type": "doubleAngle",
          "value": 0.0
        },
        "translateZ": {
          "type": "doubleLinear",
          "value": 0.0
        },
        "scaleY": {
          "type": "double",
          "value": 1.0
        },
        "translateX": {
          "type": "doubleLinear",
          "value": 0.0
        },
        "scaleX": {
          "type": "double",
          "value": 1.0
        },
        "translateY": {
          "type": "doubleLinear",
          "value": 0.0
        },
        "rotateZ": {
          "type": "doubleAngle",
          "value": 0.0
        },
        "scaleZ": {
          "type": "double",
          "value": 1.0
        },
        "rotateY": {
          "type": "doubleAngle",
          "value": 0.0
        }
      }
    },
    "FKPinkyFinger1_L": {
      "attrs": {
        "rotateX": {
          "type": "doubleAngle",
          "value": 0.0
        },
        "translateZ": {
          "type": "doubleLinear",
          "value": 0.0
        },
        "scaleY": {
          "type": "double",
          "value": 1.0
        },
        "translateX": {
          "type": "doubleLinear",
          "value": 0.0
        },
        "scaleX": {
          "type": "double",
          "value": 1.0
        },
        "translateY": {
          "type": "doubleLinear",
          "value": 0.0
        },
        "rotateZ": {
          "type": "doubleAngle",
          "value": 0.0
        },
        "scaleZ": {
          "type": "double",
          "value": 1.0
        },
        "rotateY": {
          "type": "doubleAngle",
          "value": 0.0
        }
      }
    },
    "IKhybridSpine1_M": {
      "attrs": {
        "rotateX": {
          "type": "doubleAngle",
          "value": 0.0
        },
        "translateZ": {
          "type": "doubleLinear",
          "value": 0.0
        },
        "scaleY": {
          "type": "double",
          "value": 1.0
        },
        "translateX": {
          "type": "doubleLinear",
          "value": 0.0
        },
        "scaleX": {
          "type": "double",
          "value": 1.0
        },
        "translateY": {
          "type": "doubleLinear",
          "value": 0.0
        },
        "rotateZ": {
          "type": "doubleAngle",
          "value": 0.0
        },
        "scaleZ": {
          "type": "double",
          "value": 1.0
        },
        "rotateY": {
          "type": "doubleAngle",
          "value": 0.0
        }
      }
    },
    "FKHead_M": {
      "attrs": {
        "rotateX": {
          "type": "doubleAngle",
          "value": 0.0
        },
        "Global": {
          "type": "double",
          "value": 0.0
        },
        "translateZ": {
          "type": "doubleLinear",
          "value": 0.0
        },
        "scaleY": {
          "type": "double",
          "value": 1.0
        },
        "translateX": {
          "type": "doubleLinear",
          "value": 0.0
        },
        "scaleX": {
          "type": "double",
          "value": 1.0
        },
        "translateY": {
          "type": "doubleLinear",
          "value": 0.0
        },
        "rotateZ": {
          "type": "doubleAngle",
          "value": 0.0
        },
        "scaleZ": {
          "type": "double",
          "value": 1.0
        },
        "rotateY": {
          "type": "doubleAngle",
          "value": 0.0
        }
      }
    },
    "FKMiddleFinger3_L": {
      "attrs": {
        "rotateX": {
          "type": "doubleAngle",
          "value": 0.0
        },
        "translateZ": {
          "type": "doubleLinear",
          "value": 0.0
        },
        "scaleY": {
          "type": "double",
          "value": 1.0
        },
        "translateX": {
          "type": "doubleLinear",
          "value": 0.0
        },
        "scaleX": {
          "type": "double",
          "value": 1.0
        },
        "translateY": {
          "type": "doubleLinear",
          "value": 0.0
        },
        "rotateZ": {
          "type": "doubleAngle",
          "value": 0.0
        },
        "scaleZ": {
          "type": "double",
          "value": 1.0
        },
        "rotateY": {
          "type": "doubleAngle",
          "value": 0.0
        }
      }
    },
    "FKPinkyFinger0_R": {
      "attrs": {
        "rotateX": {
          "type": "doubleAngle",
          "value": 0.0
        },
        "translateZ": {
          "type": "doubleLinear",
          "value": 0.0
        },
        "scaleY": {
          "type": "double",
          "value": 1.0
        },
        "translateX": {
          "type": "doubleLinear",
          "value": 0.0
        },
        "scaleX": {
          "type": "double",
          "value": 1.0
        },
        "translateY": {
          "type": "doubleLinear",
          "value": 0.0
        },
        "rotateZ": {
          "type": "doubleAngle",
          "value": 0.0
        },
        "scaleZ": {
          "type": "double",
          "value": 1.0
        },
        "rotateY": {
          "type": "doubleAngle",
          "value": 0.0
        }
      }
    }
  }
}